{
  "months": [
    {
      "label": "June 2025",
      "year_month": "2025-06",
      "url": "2025-06.html",
      "linkedin": {
        "organic_impressions": 19854,
        "new_followers": 399,
        "posts": 13,
        "avg_er": 13.1,
        "total_clicks": 3116,
        "total_likes": 382,
        "total_comments": 14,
        "total_shares": 26,
        "total_reactions": 396
      },
      "instagram": {
        "posts": 6,
        "total_views": 2601,
        "total_reach": 1685,
        "total_likes": 50,
        "total_comments": 0,
        "total_saves": 5,
        "total_shares": 5,
        "avg_er": 4.12,
        "followers": 2112
      },
      "combined": {
        "li_organic_impressions": 19854,
        "total_shares": 31,
        "total_reactions": 451,
        "li_avg_er": 13.1,
        "ig_avg_er": 4.12
      },
      "competitors": {
        "NEDonBoard": {
          "followers": 8827,
          "new": 68,
          "eng": 190,
          "posts": 11
        },
        "Go Fractional": {
          "followers": 6382,
          "new": 85,
          "eng": 113,
          "posts": 11
        },
        "Nurole": {
          "followers": 14211,
          "new": 82,
          "eng": 79,
          "posts": 8
        },
        "Boardsi": {
          "followers": 77846,
          "new": 517,
          "eng": 83,
          "posts": 11
        },
        "Jack & Jill": {
          "followers": 34178,
          "new": 311,
          "eng": 33,
          "posts": 2
        },
        "Intro": {
          "followers": 55023,
          "new": 367,
          "eng": 121,
          "posts": 4
        },
        "Connectd": {
          "followers": 44870,
          "new": 399,
          "eng": 392,
          "posts": 13
        },
        "Wellfound": {
          "followers": 147161,
          "new": 1966,
          "eng": 103,
          "posts": 12
        },
        "Actuate Global": {
          "followers": 6417,
          "new": 35,
          "eng": 156,
          "posts": 1
        },
        "Toptal": {
          "followers": 714845,
          "new": 2580,
          "eng": 229,
          "posts": 3
        }
      }
    },
    {
      "label": "July 2025",
      "year_month": "2025-07",
      "url": "2025-07.html",
      "linkedin": {
        "organic_impressions": 93056,
        "new_followers": 1210,
        "posts": 22,
        "avg_er": 13.2,
        "total_clicks": 6373,
        "total_likes": 1019,
        "total_comments": 115,
        "total_shares": 153,
        "total_reactions": 1134
      },
      "instagram": {
        "posts": 14,
        "total_views": 7288,
        "total_reach": 4466,
        "total_likes": 146,
        "total_comments": 0,
        "total_saves": 6,
        "total_shares": 6,
        "avg_er": 3.91,
        "followers": 2112
      },
      "combined": {
        "li_organic_impressions": 93056,
        "total_shares": 159,
        "total_reactions": 1286,
        "li_avg_er": 13.2,
        "ig_avg_er": 3.91
      },
      "competitors": {
        "NEDonBoard": {
          "followers": 8827,
          "new": 129,
          "eng": 260,
          "posts": 24
        },
        "Go Fractional": {
          "followers": 6382,
          "new": 142,
          "eng": 152,
          "posts": 23
        },
        "Nurole": {
          "followers": 14211,
          "new": 207,
          "eng": 71,
          "posts": 8
        },
        "Boardsi": {
          "followers": 77846,
          "new": 667,
          "eng": 150,
          "posts": 22
        },
        "Jack & Jill": {
          "followers": 34177,
          "new": 2699,
          "eng": 161,
          "posts": 9
        },
        "Intro": {
          "followers": 55022,
          "new": 1160,
          "eng": 688,
          "posts": 10
        },
        "Connectd": {
          "followers": 44869,
          "new": 1210,
          "eng": 1193,
          "posts": 22
        },
        "Wellfound": {
          "followers": 147161,
          "new": 3503,
          "eng": 210,
          "posts": 43
        },
        "Actuate Global": {
          "followers": 6417,
          "new": 112,
          "eng": 290,
          "posts": 4
        },
        "Toptal": {
          "followers": 714845,
          "new": 5738,
          "eng": 261,
          "posts": 4
        }
      }
    },
    {
      "label": "August 2025",
      "year_month": "2025-08",
      "url": "2025-08.html",
      "linkedin": {
        "organic_impressions": 33100,
        "new_followers": 715,
        "posts": 15,
        "avg_er": 12.1,
        "total_clicks": 2800,
        "total_likes": 339,
        "total_comments": 23,
        "total_shares": 61,
        "total_reactions": 362
      },
      "instagram": {
        "posts": 10,
        "total_views": 7489,
        "total_reach": 2466,
        "total_likes": 70,
        "total_comments": 0,
        "total_saves": 7,
        "total_shares": 3,
        "avg_er": 3.25,
        "followers": 2112
      },
      "combined": {
        "li_organic_impressions": 33100,
        "total_shares": 64,
        "total_reactions": 439,
        "li_avg_er": 12.1,
        "ig_avg_er": 3.25
      },
      "competitors": {
        "NEDonBoard": {
          "followers": 8827,
          "new": 86,
          "eng": 174,
          "posts": 16
        },
        "Go Fractional": {
          "followers": 6382,
          "new": 169,
          "eng": 165,
          "posts": 21
        },
        "Nurole": {
          "followers": 14211,
          "new": 141,
          "eng": 85,
          "posts": 11
        },
        "Boardsi": {
          "followers": 77846,
          "new": 591,
          "eng": 196,
          "posts": 21
        },
        "Jack & Jill": {
          "followers": 34177,
          "new": 1789,
          "eng": 58,
          "posts": 3
        },
        "Intro": {
          "followers": 55022,
          "new": 1383,
          "eng": 1124,
          "posts": 17
        },
        "Connectd": {
          "followers": 44865,
          "new": 715,
          "eng": 417,
          "posts": 15
        },
        "Wellfound": {
          "followers": 147161,
          "new": 2178,
          "eng": 231,
          "posts": 31
        },
        "Actuate Global": {
          "followers": 6417,
          "new": 101,
          "eng": 246,
          "posts": 2
        },
        "Toptal": {
          "followers": 714844,
          "new": 7445,
          "eng": 683,
          "posts": 5
        }
      }
    },
    {
      "label": "September 2025",
      "year_month": "2025-09",
      "url": "2025-09.html",
      "linkedin": {
        "organic_impressions": 36994,
        "new_followers": 1847,
        "posts": 17,
        "avg_er": 17.6,
        "total_clicks": 5701,
        "total_likes": 535,
        "total_comments": 50,
        "total_shares": 45,
        "total_reactions": 585
      },
      "instagram": {
        "posts": 8,
        "total_views": 2800,
        "total_reach": 2070,
        "total_likes": 70,
        "total_comments": 0,
        "total_saves": 5,
        "total_shares": 66,
        "avg_er": 5.51,
        "followers": 2112
      },
      "combined": {
        "li_organic_impressions": 36994,
        "total_shares": 111,
        "total_reactions": 660,
        "li_avg_er": 17.6,
        "ig_avg_er": 5.51
      },
      "competitors": {
        "NEDonBoard": {
          "followers": 8827,
          "new": 106,
          "eng": 277,
          "posts": 19
        },
        "Go Fractional": {
          "followers": 6382,
          "new": 256,
          "eng": 205,
          "posts": 22
        },
        "Nurole": {
          "followers": 14211,
          "new": 187,
          "eng": 87,
          "posts": 18
        },
        "Boardsi": {
          "followers": 77846,
          "new": 543,
          "eng": 231,
          "posts": 21
        },
        "Jack & Jill": {
          "followers": 34177,
          "new": 1005,
          "eng": 205,
          "posts": 7
        },
        "Intro": {
          "followers": 55022,
          "new": 631,
          "eng": 823,
          "posts": 18
        },
        "Connectd": {
          "followers": 44863,
          "new": 1847,
          "eng": 601,
          "posts": 17
        },
        "Wellfound": {
          "followers": 147159,
          "new": 1925,
          "eng": 431,
          "posts": 35
        },
        "Actuate Global": {
          "followers": 6417,
          "new": 152,
          "eng": 315,
          "posts": 13
        },
        "Toptal": {
          "followers": 714843,
          "new": 8079,
          "eng": 751,
          "posts": 4
        }
      }
    },
    {
      "label": "October 2025",
      "year_month": "2025-10",
      "url": "2025-10.html",
      "linkedin": {
        "organic_impressions": 71421,
        "new_followers": 2147,
        "posts": 23,
        "avg_er": 10.5,
        "total_clicks": 5504,
        "total_likes": 898,
        "total_comments": 55,
        "total_shares": 128,
        "total_reactions": 953
      },
      "instagram": {
        "posts": 7,
        "total_views": 7410,
        "total_reach": 1874,
        "total_likes": 96,
        "total_comments": 0,
        "total_saves": 5,
        "total_shares": 11,
        "avg_er": 3.13,
        "followers": 2112
      },
      "combined": {
        "li_organic_impressions": 71421,
        "total_shares": 139,
        "total_reactions": 1054,
        "li_avg_er": 10.5,
        "ig_avg_er": 3.13
      },
      "competitors": {
        "NEDonBoard": {
          "followers": 8827,
          "new": 131,
          "eng": 263,
          "posts": 19
        },
        "Go Fractional": {
          "followers": 6381,
          "new": 199,
          "eng": 152,
          "posts": 23
        },
        "Nurole": {
          "followers": 14211,
          "new": 215,
          "eng": 124,
          "posts": 21
        },
        "Boardsi": {
          "followers": 77845,
          "new": 652,
          "eng": 144,
          "posts": 24
        },
        "Jack & Jill": {
          "followers": 34176,
          "new": 2870,
          "eng": 1208,
          "posts": 18
        },
        "Intro": {
          "followers": 55022,
          "new": 928,
          "eng": 1275,
          "posts": 27
        },
        "Connectd": {
          "followers": 44861,
          "new": 2147,
          "eng": 996,
          "posts": 23
        },
        "Wellfound": {
          "followers": 147158,
          "new": 1714,
          "eng": 262,
          "posts": 37
        },
        "Actuate Global": {
          "followers": 6417,
          "new": 169,
          "eng": 544,
          "posts": 33
        },
        "Toptal": {
          "followers": 714836,
          "new": 9688,
          "eng": 480,
          "posts": 2
        }
      }
    },
    {
      "label": "November 2025",
      "year_month": "2025-11",
      "url": "2025-11.html",
      "linkedin": {
        "organic_impressions": 64302,
        "new_followers": 1023,
        "posts": 24,
        "avg_er": 14.5,
        "total_clicks": 8290,
        "total_likes": 839,
        "total_comments": 141,
        "total_shares": 146,
        "total_reactions": 980
      },
      "instagram": {
        "posts": 7,
        "total_views": 10478,
        "total_reach": 1945,
        "total_likes": 77,
        "total_comments": 0,
        "total_saves": 2,
        "total_shares": 7,
        "avg_er": 4.48,
        "followers": 2112
      },
      "combined": {
        "li_organic_impressions": 64302,
        "total_shares": 153,
        "total_reactions": 1059,
        "li_avg_er": 14.5,
        "ig_avg_er": 4.48
      },
      "competitors": {
        "NEDonBoard": {
          "followers": 8827,
          "new": 118,
          "eng": 251,
          "posts": 21
        },
        "Go Fractional": {
          "followers": 6379,
          "new": 192,
          "eng": 206,
          "posts": 20
        },
        "Nurole": {
          "followers": 14211,
          "new": 234,
          "eng": 69,
          "posts": 17
        },
        "Boardsi": {
          "followers": 77845,
          "new": 397,
          "eng": 101,
          "posts": 15
        },
        "Jack & Jill": {
          "followers": 34153,
          "new": 2417,
          "eng": 556,
          "posts": 4
        },
        "Intro": {
          "followers": 55021,
          "new": 751,
          "eng": 945,
          "posts": 22
        },
        "Connectd": {
          "followers": 44856,
          "new": 1228,
          "eng": 1226,
          "posts": 27
        },
        "Wellfound": {
          "followers": 147148,
          "new": 2417,
          "eng": 274,
          "posts": 32
        },
        "Actuate Global": {
          "followers": 6414,
          "new": 179,
          "eng": 303,
          "posts": 19
        },
        "Toptal": {
          "followers": 714812,
          "new": 8647,
          "eng": 601,
          "posts": 5
        }
      }
    },
    {
      "label": "December 2025",
      "year_month": "2025-12",
      "url": "2025-12.html",
      "linkedin": {
        "organic_impressions": 46391,
        "new_followers": 965,
        "posts": 13,
        "avg_er": 17.5,
        "total_clicks": 7175,
        "total_likes": 467,
        "total_comments": 27,
        "total_shares": 69,
        "total_reactions": 494
      },
      "instagram": {
        "posts": 8,
        "total_views": 15551,
        "total_reach": 3380,
        "total_likes": 96,
        "total_comments": 1,
        "total_saves": 8,
        "total_shares": 10,
        "avg_er": 3.51,
        "followers": 2112
      },
      "combined": {
        "li_organic_impressions": 46391,
        "total_shares": 79,
        "total_reactions": 599,
        "li_avg_er": 17.5,
        "ig_avg_er": 3.51
      },
      "competitors": {
        "NEDonBoard": {
          "followers": 8827,
          "new": 78,
          "eng": 242,
          "posts": 17
        },
        "Go Fractional": {
          "followers": 6379,
          "new": 231,
          "eng": 222,
          "posts": 23
        },
        "Nurole": {
          "followers": 14211,
          "new": 316,
          "eng": 3,
          "posts": 18
        },
        "Boardsi": {
          "followers": 77845,
          "new": 578,
          "eng": 175,
          "posts": 21
        },
        "Jack & Jill": {
          "followers": 34153,
          "new": 2651,
          "eng": 240,
          "posts": 9
        },
        "Intro": {
          "followers": 55021,
          "new": 927,
          "eng": 671,
          "posts": 20
        },
        "Connectd": {
          "followers": 44855,
          "new": 965,
          "eng": 572,
          "posts": 13
        },
        "Wellfound": {
          "followers": 147148,
          "new": 1829,
          "eng": 209,
          "posts": 34
        },
        "Actuate Global": {
          "followers": 6414,
          "new": 316,
          "eng": 471,
          "posts": 15
        },
        "Toptal": {
          "followers": 714810,
          "new": 6103,
          "eng": 417,
          "posts": 5
        }
      }
    },
    {
      "label": "January 2026",
      "year_month": "2026-01",
      "url": "2026-01.html",
      "linkedin": {
        "organic_impressions": 43083,
        "new_followers": 1230,
        "posts": 16,
        "avg_er": 17.8,
        "total_clicks": 5925,
        "total_likes": 566,
        "total_comments": 32,
        "total_shares": 79,
        "total_reactions": 598
      },
      "instagram": {
        "posts": 9,
        "total_views": 6335,
        "total_reach": 2544,
        "total_likes": 123,
        "total_comments": 6,
        "total_saves": 6,
        "total_shares": 9,
        "avg_er": 5.99,
        "followers": 2112
      },
      "combined": {
        "li_organic_impressions": 43083,
        "total_shares": 88,
        "total_reactions": 733,
        "li_avg_er": 17.8,
        "ig_avg_er": 5.99
      },
      "competitors": {
        "NEDonBoard": {
          "followers": 8825,
          "new": 190,
          "eng": 269,
          "posts": 19
        },
        "Go Fractional": {
          "followers": 6375,
          "new": 322,
          "eng": 227,
          "posts": 22
        },
        "Nurole": {
          "followers": 14204,
          "new": 302,
          "eng": 198,
          "posts": 18
        },
        "Boardsi": {
          "followers": 77820,
          "new": 558,
          "eng": 119,
          "posts": 20
        },
        "Jack & Jill": {
          "followers": 33986,
          "new": 5343,
          "eng": 404,
          "posts": 24
        },
        "Intro": {
          "followers": 55013,
          "new": 850,
          "eng": 1419,
          "posts": 23
        },
        "Connectd": {
          "followers": 44826,
          "new": 1230,
          "eng": 637,
          "posts": 16
        },
        "Wellfound": {
          "followers": 147129,
          "new": 2442,
          "eng": 155,
          "posts": 19
        },
        "Actuate Global": {
          "followers": 6400,
          "new": 503,
          "eng": 837,
          "posts": 14
        },
        "Toptal": {
          "followers": 714642,
          "new": 9914,
          "eng": 1320,
          "posts": 8
        }
      }
    },
    {
      "label": "February 2026",
      "year_month": "2026-02",
      "url": "2026-02.html",
      "linkedin": {
        "organic_impressions": 52893,
        "new_followers": 1331,
        "posts": 20,
        "avg_er": 19.4,
        "total_clicks": 9277,
        "total_likes": 700,
        "total_comments": 53,
        "total_shares": 93,
        "total_reactions": 753
      },
      "instagram": {
        "posts": 4,
        "total_views": 1241,
        "total_reach": 871,
        "total_likes": 27,
        "total_comments": 0,
        "total_saves": 1,
        "total_shares": 0,
        "avg_er": 3.13,
        "followers": 2112
      },
      "combined": {
        "li_organic_impressions": 52893,
        "total_shares": 93,
        "total_reactions": 781,
        "li_avg_er": 19.4,
        "ig_avg_er": 3.13
      },
      "competitors": {
        "NEDonBoard": {
          "followers": 8825,
          "new": 141,
          "eng": 222,
          "posts": 15
        },
        "Go Fractional": {
          "followers": 6375,
          "new": 419,
          "eng": 421,
          "posts": 20
        },
        "Nurole": {
          "followers": 14204,
          "new": 298,
          "eng": 291,
          "posts": 16
        },
        "Boardsi": {
          "followers": 77820,
          "new": 493,
          "eng": 126,
          "posts": 20
        },
        "Jack & Jill": {
          "followers": 33984,
          "new": 2725,
          "eng": 328,
          "posts": 13
        },
        "Intro": {
          "followers": 55013,
          "new": 640,
          "eng": 914,
          "posts": 23
        },
        "Connectd": {
          "followers": 44826,
          "new": 1331,
          "eng": 712,
          "posts": 21
        },
        "Wellfound": {
          "followers": 147128,
          "new": 1901,
          "eng": 204,
          "posts": 37
        },
        "Actuate Global": {
          "followers": 6400,
          "new": 340,
          "eng": 855,
          "posts": 21
        },
        "Toptal": {
          "followers": 714639,
          "new": 8366,
          "eng": 2102,
          "posts": 5
        }
      }
    },
    {
      "label": "March 2026",
      "year_month": "2026-03",
      "url": "2026-03.html",
      "linkedin": {
        "organic_impressions": 52803,
        "new_followers": 1313,
        "posts": 23,
        "avg_er": 15.2,
        "total_clicks": 6784,
        "total_likes": 799,
        "total_comments": 41,
        "total_shares": 87,
        "total_reactions": 840
      },
      "instagram": {
        "posts": 11,
        "total_views": 4538,
        "total_reach": 2574,
        "total_likes": 112,
        "total_comments": 5,
        "total_saves": 5,
        "total_shares": 9,
        "avg_er": 5.63,
        "followers": 2112
      },
      "combined": {
        "li_organic_impressions": 52803,
        "total_shares": 96,
        "total_reactions": 962,
        "li_avg_er": 15.2,
        "ig_avg_er": 5.63
      },
      "competitors": {
        "NEDonBoard": {
          "followers": 8825,
          "new": 129,
          "eng": 265,
          "posts": 18
        },
        "Go Fractional": {
          "followers": 6375,
          "new": 452,
          "eng": 426,
          "posts": 22
        },
        "Nurole": {
          "followers": 14203,
          "new": 340,
          "eng": 502,
          "posts": 24
        },
        "Boardsi": {
          "followers": 77820,
          "new": 557,
          "eng": 188,
          "posts": 28
        },
        "Jack & Jill": {
          "followers": 33981,
          "new": 3790,
          "eng": 1113,
          "posts": 14
        },
        "Intro": {
          "followers": 55013,
          "new": 651,
          "eng": 1185,
          "posts": 25
        },
        "Connectd": {
          "followers": 44826,
          "new": 1313,
          "eng": 969,
          "posts": 24
        },
        "Wellfound": {
          "followers": 147127,
          "new": 2481,
          "eng": 229,
          "posts": 31
        },
        "Actuate Global": {
          "followers": 6399,
          "new": 376,
          "eng": 661,
          "posts": 33
        },
        "Toptal": {
          "followers": 714638,
          "new": 6952,
          "eng": 303,
          "posts": 1
        }
      }
    },
    {
      "label": "April 2026",
      "year_month": "2026-04",
      "url": "2026-04.html",
      "linkedin": {
        "organic_impressions": 33183,
        "new_followers": 917,
        "posts": 12,
        "avg_er": 17.1,
        "total_clicks": 5460,
        "total_likes": 318,
        "total_comments": 19,
        "total_shares": 39,
        "total_reactions": 337
      },
      "instagram": {
        "posts": 5,
        "total_views": 1607,
        "total_reach": 994,
        "total_likes": 33,
        "total_comments": 1,
        "total_saves": 3,
        "total_shares": 0,
        "avg_er": 4.2,
        "followers": 2112
      },
      "combined": {
        "li_organic_impressions": 33183,
        "total_shares": 39,
        "total_reactions": 374,
        "li_avg_er": 17.1,
        "ig_avg_er": 4.2
      },
      "competitors": {
        "NEDonBoard": {
          "followers": 8825,
          "new": 113,
          "eng": 182,
          "posts": 17
        },
        "Go Fractional": {
          "followers": 6376,
          "new": 380,
          "eng": 245,
          "posts": 22
        },
        "Nurole": {
          "followers": 14203,
          "new": 306,
          "eng": 264,
          "posts": 22
        },
        "Boardsi": {
          "followers": 77820,
          "new": 483,
          "eng": 179,
          "posts": 36
        },
        "Jack & Jill": {
          "followers": 33981,
          "new": 2665,
          "eng": 546,
          "posts": 14
        },
        "Intro": {
          "followers": 55013,
          "new": 940,
          "eng": 1152,
          "posts": 20
        },
        "Connectd": {
          "followers": 44826,
          "new": 917,
          "eng": 441,
          "posts": 13
        },
        "Wellfound": {
          "followers": 147127,
          "new": 2994,
          "eng": 221,
          "posts": 23
        },
        "Actuate Global": {
          "followers": 6399,
          "new": 482,
          "eng": 1027,
          "posts": 43
        },
        "Toptal": {
          "followers": 714635,
          "new": 7433,
          "eng": 326,
          "posts": 4
        }
      }
    },
    {
      "label": "May 2026",
      "year_month": "2026-05",
      "url": "2026-05.html",
      "linkedin": {
        "organic_impressions": 55609,
        "total_impressions": 81805,
        "new_followers": 1593,
        "posts": 12,
        "avg_er": 17.4,
        "total_clicks": 7454,
        "total_likes": 1430,
        "total_comments": 179,
        "total_shares": 84,
        "total_reactions": 1609
      },
      "instagram": {
        "total_views": 1549,
        "total_reach": 982,
        "total_likes": 40,
        "total_comments": 1,
        "total_saves": 2,
        "total_shares": 2,
        "avg_er": 4.56,
        "posts": 5,
        "followers": 2112
      },
      "combined": {
        "li_organic_impressions": 55609,
        "total_impressions": 83354,
        "total_shares": 86,
        "total_reactions": 1652,
        "li_avg_er": 17.4,
        "ig_avg_er": 4.56
      },
      "competitors": {
        "NEDonBoard": {
          "followers": 8785,
          "new": 114,
          "eng": 155,
          "posts": 14
        },
        "Go Fractional": {
          "followers": 6269,
          "new": 379,
          "eng": 277,
          "posts": 22
        },
        "Nurole": {
          "followers": 14115,
          "new": 237,
          "eng": 312,
          "posts": 17
        },
        "Boardsi": {
          "followers": 77591,
          "new": 634,
          "eng": 188,
          "posts": 43
        },
        "Jack & Jill": {
          "followers": 32563,
          "new": 2645,
          "eng": 537,
          "posts": 21
        },
        "Intro": {
          "followers": 54667,
          "new": 897,
          "eng": 1206,
          "posts": 20
        },
        "Connectd": {
          "followers": 44085,
          "new": 1593,
          "eng": 355,
          "posts": 12
        },
        "Wellfound": {
          "followers": 146234,
          "new": 2295,
          "eng": 44,
          "posts": 1
        },
        "Actuate Global": {
          "followers": 6144,
          "new": 652,
          "eng": 1781,
          "posts": 58
        },
        "Toptal": {
          "followers": 712393,
          "new": 6790,
          "eng": 742,
          "posts": 3
        }
      }
    }
  ]
}